mathsample101/__init__.py
mathsample101/math_test.py
mathsample101-0.0.3.dist-info/METADATA
mathsample101-0.0.3.dist-info/WHEEL
mathsample101-0.0.3.dist-info/top_level.txt
mathsample101-0.0.3.dist-info/RECORD
